[
    {
        "username": "sparklingsoul", 
        "user_firstname": "", 
        "user_lastname": "", 
        "created_at": "2023-05-30T18:40:02.002370+02:00", 
        "telephone": "+43650999889", 
        "email": "sparklingsoul@example.com", 
        "liked_posts": [
            2464
        ], 
        "banana_points": 0, 
        "profile_img": "/images/blankuser/profile_image.png", 
        "active": true, 
        "id": 981
    }, 
    {
        "username": "playfulpixie", 
        "user_firstname": "", 
        "user_lastname": "", 
        "created_at": "2023-05-30T18:40:02.088707+02:00", 
        "telephone": "+43650748557", 
        "id": 982, 
        "liked_posts": [
            2428, 
            2624, 
            2671, 
            2459
        ], 
        "banana_points": 0, 
        "profile_img": "/images/blankuser/profile_image.png", 
        "active": true, 
        "email": "playfulpixie@foo.com"
    }, 
    {
        "username": "fairywhisperer", 
        "user_firstname": "", 
        "user_lastname": "", 
        "created_at": "2023-05-30T18:40:02.127551+02:00", 
        "telephone": "+43650301062", 
        "email": "fairywhisperer@foo.com", 
        "liked_posts": [
            2534, 
            2468, 
            2480, 
            2683, 
            2483, 
            2642
        ], 
        "banana_points": 0, 
        "profile_img": "/images/blankuser/profile_image.png", 
        "active": true, 
        "id": 983
    }, 
    {
        "username": "celestialdreamer", 
        "user_firstname": "", 
        "user_lastname": "", 
        "created_at": "2023-05-30T18:40:02.178593+02:00", 
        "telephone": "+43650161690", 
        "id": 984, 
        "liked_posts": [
            2465, 
            2515, 
            2582, 
            2640, 
            2670, 
            2449, 
            2414, 
            2432, 
            2650, 
            2592, 
            2531
        ], 
        "banana_points": 0, 
        "profile_img": "/images/blankuser/profile_image.png", 
        "active": true, 
        "email": "celestialdreamer@example.com"
    }, 
    {
        "username": "dreamydaydream", 
        "user_firstname": "", 
        "user_lastname": "", 
        "created_at": "2023-05-30T18:40:02.217750+02:00", 
        "telephone": "+43650321580", 
        "email": "dreamydaydream@test.com", 
        "liked_posts": [
            2683, 
            2456, 
            2632, 
            2656
        ], 
        "banana_points": 0, 
        "profile_img": "/images/blankuser/profile_image.png", 
        "active": true, 
        "id": 985
    }, 
    {
        "username": "charmedtraveller", 
        "user_firstname": "", 
        "user_lastname": "", 
        "created_at": "2023-05-30T18:40:02.253847+02:00", 
        "telephone": "+43650326777", 
        "id": 986, 
        "liked_posts": [
            2519, 
            2585, 
            2614, 
            2431
        ], 
        "banana_points": 0, 
        "profile_img": "/images/blankuser/profile_image.png", 
        "active": true, 
        "email": "charmedtraveller@test.com"
    }, 
    {
        "username": "fancifulroamer", 
        "user_firstname": "", 
        "user_lastname": "", 
        "created_at": "2023-05-30T18:40:02.289909+02:00", 
        "telephone": "+43650653706", 
        "email": "fancifulroamer@test.com", 
        "liked_posts": [
            2539, 
            2462, 
            2492
        ], 
        "banana_points": 0, 
        "profile_img": "/images/blankuser/profile_image.png", 
        "active": true, 
        "id": 987
    }, 
    {
        "username": "mirthfulmuse", 
        "user_firstname": "", 
        "user_lastname": "", 
        "created_at": "2023-05-30T18:40:02.325600+02:00", 
        "telephone": "+43650842649", 
        "id": 988, 
        "liked_posts": [
            2604, 
            2632, 
            2483
        ], 
        "banana_points": 0, 
        "profile_img": "/images/blankuser/profile_image.png", 
        "active": true, 
        "email": "mirthfulmuse@foo.com"
    }, 
    {
        "username": "fantasticalquest", 
        "user_firstname": "", 
        "user_lastname": "", 
        "created_at": "2023-05-30T18:40:02.364557+02:00", 
        "telephone": "+43650749213", 
        "email": "fantasticalquest@test.com", 
        "active": true, 
        "banana_points": 0, 
        "profile_img": "/images/blankuser/profile_image.png", 
        "liked_posts": [
            2455, 
            2644
        ], 
        "id": 989
    }, 
    {
        "username": "dreamydaydream", 
        "user_firstname": "", 
        "user_lastname": "", 
        "created_at": "2023-05-30T18:40:02.411871+02:00", 
        "telephone": "+43650587910", 
        "id": 990, 
        "active": true, 
        "banana_points": 0, 
        "profile_img": "/images/blankuser/profile_image.png", 
        "liked_posts": [
            2464, 
            2613, 
            2483, 
            2523, 
            2469
        ], 
        "email": "dreamydaydream@example.com"
    }, 
    {
        "username": "mysticalitinerant", 
        "user_firstname": "", 
        "user_lastname": "", 
        "created_at": "2023-05-30T18:40:02.448017+02:00", 
        "telephone": "+43650168987", 
        "email": "mysticalitinerant@example.com", 
        "active": true, 
        "banana_points": 0, 
        "profile_img": "/images/blankuser/profile_image.png", 
        "liked_posts": [
            2578, 
            2539, 
            2494, 
            2651, 
            2436
        ], 
        "id": 991
    }, 
    {
        "username": "fantasyquest", 
        "user_firstname": "", 
        "user_lastname": "", 
        "created_at": "2023-05-30T18:40:02.486019+02:00", 
        "telephone": "+43650315631", 
        "id": 992, 
        "liked_posts": [
            2667, 
            2602, 
            2661, 
            2700, 
            2456
        ], 
        "banana_points": 0, 
        "profile_img": "/images/blankuser/profile_image.png", 
        "active": true, 
        "email": "fantasyquest@test.com"
    }, 
    {
        "username": "spellbindingseeker", 
        "user_firstname": "", 
        "user_lastname": "", 
        "created_at": "2023-05-30T18:40:02.524496+02:00", 
        "telephone": "+43650227820", 
        "email": "spellbindingseeker@foo.com", 
        "active": true, 
        "banana_points": 0, 
        "profile_img": "/images/blankuser/profile_image.png", 
        "liked_posts": [
            2689
        ], 
        "id": 993
    }, 
    {
        "username": "wanderingwhisper", 
        "user_firstname": "", 
        "user_lastname": "", 
        "created_at": "2023-05-30T18:40:02.577728+02:00", 
        "telephone": "+43650917164", 
        "id": 994, 
        "active": true, 
        "banana_points": 0, 
        "profile_img": "/images/blankuser/profile_image.png", 
        "liked_posts": [
            2547, 
            2695, 
            2576, 
            2457
        ], 
        "email": "wanderingwhisper@example.com"
    }, 
    {
        "username": "bewitchedexplorer", 
        "user_firstname": "", 
        "user_lastname": "", 
        "created_at": "2023-05-30T18:40:02.624199+02:00", 
        "telephone": "+43650117393", 
        "email": "bewitchedexplorer@foo.com", 
        "liked_posts": [
            2671, 
            2674, 
            2508, 
            2517, 
            2689, 
            2419, 
            2561
        ], 
        "banana_points": 0, 
        "profile_img": "/images/blankuser/profile_image.png", 
        "active": true, 
        "id": 995
    }, 
    {
        "username": "enigmaticentity", 
        "user_firstname": "", 
        "user_lastname": "", 
        "created_at": "2023-05-30T18:40:02.690716+02:00", 
        "telephone": "+43650521703", 
        "id": 996, 
        "liked_posts": [
            2474, 
            2678, 
            2614
        ], 
        "banana_points": 0, 
        "profile_img": "/images/blankuser/profile_image.png", 
        "active": true, 
        "email": "enigmaticentity@foo.com"
    }, 
    {
        "username": "curiouswanderlust", 
        "user_firstname": "", 
        "user_lastname": "", 
        "created_at": "2023-05-30T18:40:02.734142+02:00", 
        "telephone": "+43650494733", 
        "email": "curiouswanderlust@test.com", 
        "active": true, 
        "banana_points": 0, 
        "profile_img": "/images/blankuser/profile_image.png", 
        "liked_posts": [
            2563, 
            2483
        ], 
        "id": 997
    }, 
    {
        "username": "aetherialadventurer", 
        "user_firstname": "", 
        "user_lastname": "", 
        "created_at": "2023-05-30T18:40:02.779376+02:00", 
        "telephone": "+43650225862", 
        "id": 998, 
        "liked_posts": [
            2628, 
            2590, 
            2443, 
            2460, 
            2582, 
            2507, 
            2626, 
            2414, 
            2517
        ], 
        "banana_points": 0, 
        "profile_img": "/images/blankuser/profile_image.png", 
        "active": true, 
        "email": "aetherialadventurer@foo.com"
    }, 
    {
        "username": "mysticalitinerant", 
        "user_firstname": "", 
        "user_lastname": "", 
        "created_at": "2023-05-30T18:40:02.836610+02:00", 
        "telephone": "+43650297350", 
        "email": "mysticalitinerant@foo.com", 
        "liked_posts": [
            2452, 
            2685, 
            2654, 
            2598
        ], 
        "banana_points": 0, 
        "profile_img": "/images/blankuser/profile_image.png", 
        "active": true, 
        "id": 999
    }, 
    {
        "username": "fabledadventurer", 
        "user_firstname": "", 
        "user_lastname": "", 
        "created_at": "2023-05-30T18:40:02.939910+02:00", 
        "telephone": "+43650965100", 
        "id": 1000, 
        "active": true, 
        "banana_points": 0, 
        "profile_img": "/images/blankuser/profile_image.png", 
        "liked_posts": [
            2482, 
            2489, 
            2522, 
            2515
        ], 
        "email": "fabledadventurer@example.com"
    }, 
    {
        "username": "bewilderednomad", 
        "user_firstname": "", 
        "user_lastname": "", 
        "created_at": "2023-05-30T18:40:02.997639+02:00", 
        "telephone": "+43650849452", 
        "email": "bewilderednomad@test.com", 
        "active": true, 
        "banana_points": 0, 
        "profile_img": "/images/blankuser/profile_image.png", 
        "liked_posts": [
            2675, 
            2632, 
            2455, 
            2687, 
            2585, 
            2495, 
            2623
        ], 
        "id": 1001
    }, 
    {
        "username": "mysticalitinerant", 
        "user_firstname": "", 
        "user_lastname": "", 
        "created_at": "2023-05-30T18:40:03.042181+02:00", 
        "telephone": "+43650139201", 
        "id": 1002, 
        "liked_posts": [
            2705, 
            2465, 
            2670, 
            2633, 
            2417, 
            2552, 
            2512, 
            2713
        ], 
        "banana_points": 0, 
        "profile_img": "/images/blankuser/profile_image.png", 
        "active": true, 
        "email": "mysticalitinerant@test.com"
    }, 
    {
        "username": "mirthfulmuse", 
        "user_firstname": "", 
        "user_lastname": "", 
        "created_at": "2023-05-30T18:40:03.078198+02:00", 
        "telephone": "+43650913744", 
        "email": "mirthfulmuse@example.com", 
        "active": true, 
        "banana_points": 0, 
        "profile_img": "/images/blankuser/profile_image.png", 
        "liked_posts": [
            2569, 
            2510, 
            2577, 
            2710, 
            2707, 
            2580
        ], 
        "id": 1003
    }, 
    {
        "username": "whisperedwanderer", 
        "user_firstname": "", 
        "user_lastname": "", 
        "created_at": "2023-05-30T18:40:03.117119+02:00", 
        "telephone": "+43650093247", 
        "id": 1004, 
        "banana_points": 0, 
        "profile_img": "/images/blankuser/profile_image.png", 
        "active": true, 
        "email": "whisperedwanderer@example.com"
    }, 
    {
        "username": "tricklingwisp", 
        "user_firstname": "", 
        "user_lastname": "", 
        "created_at": "2023-05-30T18:40:03.156191+02:00", 
        "telephone": "+43650655428", 
        "email": "tricklingwisp@foo.com", 
        "active": true, 
        "banana_points": 0, 
        "profile_img": "/images/blankuser/profile_image.png", 
        "liked_posts": [
            2465, 
            2452, 
            2482, 
            2514, 
            2438, 
            2661, 
            2585
        ], 
        "id": 1005
    }, 
    {
        "username": "midnightmarauder", 
        "user_firstname": "", 
        "user_lastname": "", 
        "created_at": "2023-05-30T18:40:03.200509+02:00", 
        "telephone": "+43650166030", 
        "id": 1006, 
        "liked_posts": [
            2464, 
            2571, 
            2638, 
            2712, 
            2640
        ], 
        "banana_points": 0, 
        "profile_img": "/images/blankuser/profile_image.png", 
        "active": true, 
        "email": "midnightmarauder@test.com"
    }, 
    {
        "username": "serendipitysearcher", 
        "user_firstname": "", 
        "user_lastname": "", 
        "created_at": "2023-05-30T18:40:03.252707+02:00", 
        "telephone": "+43650206724", 
        "email": "serendipitysearcher@foo.com", 
        "active": true, 
        "banana_points": 0, 
        "profile_img": "/images/blankuser/profile_image.png", 
        "liked_posts": [
            2601, 
            2618, 
            2509
        ], 
        "id": 1007
    }, 
    {
        "username": "enchantingecho", 
        "user_firstname": "", 
        "user_lastname": "", 
        "created_at": "2023-05-30T18:40:03.293862+02:00", 
        "telephone": "+43650603654", 
        "id": 1008, 
        "liked_posts": [
            2675, 
            2678, 
            2598, 
            2614
        ], 
        "banana_points": 0, 
        "profile_img": "/images/blankuser/profile_image.png", 
        "active": true, 
        "email": "enchantingecho@example.com"
    }, 
    {
        "username": "velvetvoyager", 
        "user_firstname": "", 
        "user_lastname": "", 
        "created_at": "2023-05-30T18:40:03.335628+02:00", 
        "telephone": "+43650513126", 
        "email": "velvetvoyager@test.com", 
        "liked_posts": [
            2666
        ], 
        "banana_points": 0, 
        "profile_img": "/images/blankuser/profile_image.png", 
        "active": true, 
        "id": 1009
    }, 
    {
        "username": "wanderingwhisper", 
        "user_firstname": "", 
        "user_lastname": "", 
        "created_at": "2023-05-30T18:40:03.373026+02:00", 
        "telephone": "+43650993146", 
        "id": 1010, 
        "liked_posts": [
            2658, 
            2616, 
            2606, 
            2601, 
            2567
        ], 
        "banana_points": 0, 
        "profile_img": "/images/blankuser/profile_image.png", 
        "active": true, 
        "email": "wanderingwhisper@test.com"
    }, 
    {
        "username": "wanderingwonder", 
        "user_firstname": "", 
        "user_lastname": "", 
        "created_at": "2023-05-30T18:40:03.410669+02:00", 
        "telephone": "+43650062341", 
        "email": "wanderingwonder@foo.com", 
        "liked_posts": [
            2511, 
            2461, 
            2444, 
            2569, 
            2623, 
            2583
        ], 
        "banana_points": 0, 
        "profile_img": "/images/blankuser/profile_image.png", 
        "active": true, 
        "id": 1011
    }, 
    {
        "username": "moonlitmystery", 
        "user_firstname": "", 
        "user_lastname": "", 
        "created_at": "2023-05-30T18:40:03.446068+02:00", 
        "telephone": "+43650945662", 
        "id": 1012, 
        "liked_posts": [
            2417, 
            2613, 
            2577, 
            2438, 
            2671, 
            2654
        ], 
        "banana_points": 0, 
        "profile_img": "/images/blankuser/profile_image.png", 
        "active": true, 
        "email": "moonlitmystery@test.com"
    }, 
    {
        "username": "enchantingdreamer", 
        "user_firstname": "", 
        "user_lastname": "", 
        "created_at": "2023-05-30T18:40:03.527597+02:00", 
        "telephone": "+43650325381", 
        "email": "enchantingdreamer@test.com", 
        "liked_posts": [
            2695, 
            2667, 
            2630
        ], 
        "banana_points": 0, 
        "profile_img": "/images/blankuser/profile_image.png", 
        "active": true, 
        "id": 1013
    }, 
    {
        "username": "mysteriousroamer", 
        "user_firstname": "", 
        "user_lastname": "", 
        "created_at": "2023-05-30T18:40:03.564789+02:00", 
        "telephone": "+43650000758", 
        "id": 1014, 
        "liked_posts": [
            2549, 
            2680
        ], 
        "banana_points": 0, 
        "profile_img": "/images/blankuser/profile_image.png", 
        "active": true, 
        "email": "mysteriousroamer@test.com"
    }, 
    {
        "username": "luminarydreamer", 
        "user_firstname": "", 
        "user_lastname": "", 
        "created_at": "2023-05-30T18:40:03.607256+02:00", 
        "telephone": "+43650781643", 
        "email": "luminarydreamer@example.com", 
        "liked_posts": [
            2709, 
            2530, 
            2669
        ], 
        "banana_points": 0, 
        "profile_img": "/images/blankuser/profile_image.png", 
        "active": true, 
        "id": 1015
    }, 
    {
        "username": "enigmaticwanderer", 
        "user_firstname": "", 
        "user_lastname": "", 
        "created_at": "2023-05-30T18:40:03.666280+02:00", 
        "telephone": "+43650215912", 
        "id": 1016, 
        "liked_posts": [
            2489
        ], 
        "banana_points": 0, 
        "profile_img": "/images/blankuser/profile_image.png", 
        "active": true, 
        "email": "enigmaticwanderer@test.com"
    }, 
    {
        "username": "inspiringwanderer", 
        "user_firstname": "", 
        "user_lastname": "", 
        "created_at": "2023-05-30T18:40:03.746103+02:00", 
        "telephone": "+43650827996", 
        "email": "inspiringwanderer@test.com", 
        "active": true, 
        "banana_points": 0, 
        "profile_img": "/images/blankuser/profile_image.png", 
        "liked_posts": [
            2675, 
            2702, 
            2531
        ], 
        "id": 1017
    }, 
    {
        "username": "whimsicalitinerant", 
        "user_firstname": "", 
        "user_lastname": "", 
        "created_at": "2023-05-30T18:40:03.829669+02:00", 
        "telephone": "+43650595479", 
        "id": 1018, 
        "active": true, 
        "banana_points": 0, 
        "profile_img": "/images/blankuser/profile_image.png", 
        "liked_posts": [
            2486, 
            2621
        ], 
        "email": "whimsicalitinerant@foo.com"
    }, 
    {
        "username": "techguru", 
        "user_firstname": "", 
        "user_lastname": "", 
        "created_at": "2023-05-30T18:40:03.870984+02:00", 
        "telephone": "+43650533773", 
        "email": "techguru@test.com", 
        "liked_posts": [
            2522, 
            2675, 
            2581, 
            2566, 
            2615, 
            2611, 
            2689, 
            2417, 
            2548, 
            2543
        ], 
        "banana_points": 0, 
        "profile_img": "/images/blankuser/profile_image.png", 
        "active": true, 
        "id": 1019
    }, 
    {
        "username": "curiouspixie", 
        "user_firstname": "", 
        "user_lastname": "", 
        "created_at": "2023-05-30T18:40:03.908976+02:00", 
        "telephone": "+43650787540", 
        "id": 1020, 
        "active": true, 
        "banana_points": 0, 
        "profile_img": "/images/blankuser/profile_image.png", 
        "liked_posts": [
            2642, 
            2516, 
            2655
        ], 
        "email": "curiouspixie@example.com"
    }, 
    {
        "username": "curiouspixie", 
        "user_firstname": "", 
        "user_lastname": "", 
        "created_at": "2023-05-30T18:40:03.948435+02:00", 
        "telephone": "+43650836411", 
        "email": "curiouspixie@test.com", 
        "active": true, 
        "banana_points": 0, 
        "profile_img": "/images/blankuser/profile_image.png", 
        "liked_posts": [
            2479, 
            2445, 
            2618, 
            2452, 
            2623, 
            2427, 
            2500
        ], 
        "id": 1021
    }, 
    {
        "username": "serendipitousmuse", 
        "user_firstname": "", 
        "user_lastname": "", 
        "created_at": "2023-05-30T18:40:03.986844+02:00", 
        "telephone": "+43650905654", 
        "id": 1022, 
        "liked_posts": [
            2656, 
            2539, 
            2678, 
            2572
        ], 
        "banana_points": 0, 
        "profile_img": "/images/blankuser/profile_image.png", 
        "active": true, 
        "email": "serendipitousmuse@example.com"
    }, 
    {
        "username": "silkysmooth", 
        "user_firstname": "", 
        "user_lastname": "", 
        "created_at": "2023-05-30T18:40:04.061102+02:00", 
        "telephone": "+43650064574", 
        "email": "silkysmooth@foo.com", 
        "liked_posts": [
            2622, 
            2582, 
            2491
        ], 
        "banana_points": 0, 
        "profile_img": "/images/blankuser/profile_image.png", 
        "active": true, 
        "id": 1023
    }, 
    {
        "username": "aerialdreamer", 
        "user_firstname": "", 
        "user_lastname": "", 
        "created_at": "2023-05-30T18:40:04.103489+02:00", 
        "telephone": "+43650007832", 
        "id": 1024, 
        "active": true, 
        "banana_points": 0, 
        "profile_img": "/images/blankuser/profile_image.png", 
        "liked_posts": [
            2653, 
            2606, 
            2709
        ], 
        "email": "aerialdreamer@foo.com"
    }, 
    {
        "username": "fantasticalseeker", 
        "user_firstname": "", 
        "user_lastname": "", 
        "created_at": "2023-05-30T18:40:04.146217+02:00", 
        "telephone": "+43650281630", 
        "email": "fantasticalseeker@example.com", 
        "liked_posts": [
            2467
        ], 
        "banana_points": 0, 
        "profile_img": "/images/blankuser/profile_image.png", 
        "active": true, 
        "id": 1025
    }, 
    {
        "username": "fabledadventurer", 
        "user_firstname": "", 
        "user_lastname": "", 
        "created_at": "2023-05-30T18:40:04.184619+02:00", 
        "telephone": "+43650305683", 
        "id": 1026, 
        "active": true, 
        "banana_points": 0, 
        "profile_img": "/images/blankuser/profile_image.png", 
        "liked_posts": [
            2646, 
            2616, 
            2428, 
            2606
        ], 
        "email": "fabledadventurer@foo.com"
    }, 
    {
        "username": "dreamingwanderlust", 
        "user_firstname": "", 
        "user_lastname": "", 
        "created_at": "2023-05-30T18:40:04.222875+02:00", 
        "telephone": "+43650332538", 
        "email": "dreamingwanderlust@foo.com", 
        "active": true, 
        "banana_points": 0, 
        "profile_img": "/images/blankuser/profile_image.png", 
        "liked_posts": [
            2531, 
            2704, 
            2710
        ], 
        "id": 1027
    }, 
    {
        "username": "effervescentecho", 
        "user_firstname": "", 
        "user_lastname": "", 
        "created_at": "2023-05-30T18:40:04.429150+02:00", 
        "telephone": "+43650732832", 
        "id": 1028, 
        "liked_posts": [
            2613, 
            2475, 
            2652
        ], 
        "banana_points": 0, 
        "profile_img": "/images/blankuser/profile_image.png", 
        "active": true, 
        "email": "effervescentecho@test.com"
    }, 
    {
        "username": "sparklingspirit", 
        "user_firstname": "", 
        "user_lastname": "", 
        "created_at": "2023-05-30T18:40:04.468799+02:00", 
        "telephone": "+43650013577", 
        "email": "sparklingspirit@test.com", 
        "liked_posts": [
            2455, 
            2496, 
            2606, 
            2551, 
            2416, 
            2493
        ], 
        "banana_points": 0, 
        "profile_img": "/images/blankuser/profile_image.png", 
        "active": true, 
        "id": 1029
    }, 
    {
        "username": "wanderingwhisper", 
        "user_firstname": "", 
        "user_lastname": "", 
        "created_at": "2023-05-30T18:40:04.541286+02:00", 
        "telephone": "+43650743324", 
        "id": 1030, 
        "liked_posts": [
            2452, 
            2485, 
            2575, 
            2457, 
            2433, 
            2467
        ], 
        "banana_points": 0, 
        "profile_img": "/images/blankuser/profile_image.png", 
        "active": true, 
        "email": "wanderingwhisper@foo.com"
    }, 
    {
        "username": "sparklinginsight", 
        "user_firstname": "", 
        "user_lastname": "", 
        "created_at": "2023-05-30T18:40:04.608280+02:00", 
        "telephone": "+43650066147", 
        "email": "sparklinginsight@test.com", 
        "active": true, 
        "banana_points": 0, 
        "profile_img": "/images/blankuser/profile_image.png", 
        "liked_posts": [
            2711
        ], 
        "id": 1031
    }, 
    {
        "username": "captivatingquest", 
        "user_firstname": "", 
        "user_lastname": "", 
        "created_at": "2023-05-30T18:40:04.667301+02:00", 
        "telephone": "+43650089637", 
        "id": 1032, 
        "liked_posts": [
            2509, 
            2510
        ], 
        "banana_points": 0, 
        "profile_img": "/images/blankuser/profile_image.png", 
        "active": true, 
        "email": "captivatingquest@example.com"
    }, 
    {
        "username": "whimsicalitinerant", 
        "user_firstname": "", 
        "user_lastname": "", 
        "created_at": "2023-05-30T18:40:04.727047+02:00", 
        "telephone": "+43650052311", 
        "email": "whimsicalitinerant@test.com", 
        "active": true, 
        "banana_points": 0, 
        "profile_img": "/images/blankuser/profile_image.png", 
        "liked_posts": [
            2478, 
            2543, 
            2428
        ], 
        "id": 1033
    }, 
    {
        "username": "fairywhisperer", 
        "user_firstname": "", 
        "user_lastname": "", 
        "created_at": "2023-05-30T18:40:04.787203+02:00", 
        "telephone": "+43650506983", 
        "id": 1034, 
        "liked_posts": [
            2461, 
            2627, 
            2486, 
            2584
        ], 
        "banana_points": 0, 
        "profile_img": "/images/blankuser/profile_image.png", 
        "active": true, 
        "email": "fairywhisperer@example.com"
    }, 
    {
        "username": "mysticadventurer", 
        "user_firstname": "", 
        "user_lastname": "", 
        "created_at": "2023-05-30T18:40:04.848831+02:00", 
        "telephone": "+43650223705", 
        "email": "mysticadventurer@example.com", 
        "liked_posts": [
            2497, 
            2585, 
            2459, 
            2536, 
            2613, 
            2520
        ], 
        "banana_points": 0, 
        "profile_img": "/images/blankuser/profile_image.png", 
        "active": true, 
        "id": 1035
    }, 
    {
        "username": "celestialdreamer", 
        "user_firstname": "", 
        "user_lastname": "", 
        "created_at": "2023-05-30T18:40:04.919239+02:00", 
        "telephone": "+43650006563", 
        "id": 1036, 
        "active": true, 
        "banana_points": 0, 
        "profile_img": "/images/blankuser/profile_image.png", 
        "liked_posts": [
            2429, 
            2457, 
            2425, 
            2446, 
            2430
        ], 
        "email": "celestialdreamer@test.com"
    }, 
    {
        "username": "enchantingdreamer", 
        "user_firstname": "", 
        "user_lastname": "", 
        "created_at": "2023-05-30T18:40:05.010549+02:00", 
        "telephone": "+43650459719", 
        "email": "enchantingdreamer@example.com", 
        "liked_posts": [
            2574, 
            2470, 
            2638, 
            2523, 
            2488, 
            2490
        ], 
        "banana_points": 0, 
        "profile_img": "/images/blankuser/profile_image.png", 
        "active": true, 
        "id": 1037
    }, 
    {
        "username": "serendipitousseeker", 
        "user_firstname": "", 
        "user_lastname": "", 
        "created_at": "2023-05-30T18:40:05.095024+02:00", 
        "telephone": "+43650710160", 
        "id": 1038, 
        "active": true, 
        "banana_points": 0, 
        "profile_img": "/images/blankuser/profile_image.png", 
        "liked_posts": [
            2436, 
            2559
        ], 
        "email": "serendipitousseeker@example.com"
    }, 
    {
        "username": "enigmaticwanderer", 
        "user_firstname": "", 
        "user_lastname": "", 
        "created_at": "2023-05-30T18:40:05.216966+02:00", 
        "telephone": "+43650078266", 
        "email": "enigmaticwanderer@foo.com", 
        "active": true, 
        "banana_points": 0, 
        "profile_img": "/images/blankuser/profile_image.png", 
        "liked_posts": [
            2581, 
            2691, 
            2548, 
            2586
        ], 
        "id": 1039
    }, 
    {
        "username": "imaginativeitinerant", 
        "user_firstname": "", 
        "user_lastname": "", 
        "created_at": "2023-05-30T18:40:05.273397+02:00", 
        "telephone": "+43650056317", 
        "id": 1040, 
        "active": true, 
        "banana_points": 0, 
        "profile_img": "/images/blankuser/profile_image.png", 
        "liked_posts": [
            2631, 
            2478, 
            2450, 
            2451, 
            2418
        ], 
        "email": "imaginativeitinerant@foo.com"
    }, 
    {
        "username": "playfulpixie", 
        "user_firstname": "", 
        "user_lastname": "", 
        "created_at": "2023-05-30T18:40:05.325549+02:00", 
        "telephone": "+43650557454", 
        "email": "playfulpixie@test.com", 
        "liked_posts": [
            2426, 
            2517
        ], 
        "banana_points": 0, 
        "profile_img": "/images/blankuser/profile_image.png", 
        "active": true, 
        "id": 1041
    }, 
    {
        "username": "aerialdreamer", 
        "user_firstname": "", 
        "user_lastname": "", 
        "created_at": "2023-05-30T18:40:05.422091+02:00", 
        "telephone": "+43650679440", 
        "id": 1042, 
        "liked_posts": [
            2527, 
            2580, 
            2583
        ], 
        "banana_points": 0, 
        "profile_img": "/images/blankuser/profile_image.png", 
        "active": true, 
        "email": "aerialdreamer@example.com"
    }, 
    {
        "username": "wanderingwhimsy", 
        "user_firstname": "", 
        "user_lastname": "", 
        "created_at": "2023-05-30T18:40:05.492026+02:00", 
        "telephone": "+43650284421", 
        "email": "wanderingwhimsy@example.com", 
        "active": true, 
        "banana_points": 0, 
        "profile_img": "/images/blankuser/profile_image.png", 
        "liked_posts": [
            2689, 
            2427, 
            2516, 
            2579, 
            2575
        ], 
        "id": 1043
    }, 
    {
        "username": "luminarydreamer", 
        "user_firstname": "", 
        "user_lastname": "", 
        "created_at": "2023-05-30T18:40:05.546406+02:00", 
        "telephone": "+43650335622", 
        "id": 1044, 
        "active": true, 
        "banana_points": 0, 
        "profile_img": "/images/blankuser/profile_image.png", 
        "liked_posts": [
            2457, 
            2681
        ], 
        "email": "luminarydreamer@foo.com"
    }, 
    {
        "username": "goldenmuse", 
        "user_firstname": "", 
        "user_lastname": "", 
        "created_at": "2023-05-30T18:40:05.586731+02:00", 
        "telephone": "+43650415788", 
        "email": "goldenmuse@example.com", 
        "active": true, 
        "banana_points": 0, 
        "profile_img": "/images/blankuser/profile_image.png", 
        "liked_posts": [
            2564, 
            2649, 
            2552, 
            2499
        ], 
        "id": 1045
    }, 
    {
        "username": "sparklingspirit", 
        "user_firstname": "", 
        "user_lastname": "", 
        "created_at": "2023-05-30T18:40:05.632358+02:00", 
        "telephone": "+43650479628", 
        "id": 1046, 
        "liked_posts": [
            2568, 
            2511, 
            2579
        ], 
        "banana_points": 0, 
        "profile_img": "/images/blankuser/profile_image.png", 
        "active": true, 
        "email": "sparklingspirit@foo.com"
    }, 
    {
        "username": "etherealwanderlust", 
        "user_firstname": "", 
        "user_lastname": "", 
        "created_at": "2023-05-30T18:40:05.681773+02:00", 
        "telephone": "+43650801065", 
        "email": "etherealwanderlust@test.com", 
        "active": true, 
        "banana_points": 0, 
        "profile_img": "/images/blankuser/profile_image.png", 
        "liked_posts": [
            2677, 
            2609, 
            2429, 
            2647, 
            2595
        ], 
        "id": 1047
    }, 
    {
        "username": "stellaradventurer", 
        "user_firstname": "", 
        "user_lastname": "", 
        "created_at": "2023-05-30T18:40:05.743754+02:00", 
        "telephone": "+43650766076", 
        "id": 1048, 
        "active": true, 
        "banana_points": 0, 
        "profile_img": "/images/blankuser/profile_image.png", 
        "liked_posts": [
            2613, 
            2475, 
            2628, 
            2696
        ], 
        "email": "stellaradventurer@example.com"
    }, 
    {
        "username": "curiouswanderlust", 
        "user_firstname": "", 
        "user_lastname": "", 
        "created_at": "2023-05-30T18:40:05.785813+02:00", 
        "telephone": "+43650586954", 
        "email": "curiouswanderlust@foo.com", 
        "active": true, 
        "banana_points": 0, 
        "profile_img": "/images/blankuser/profile_image.png", 
        "liked_posts": [
            2425, 
            2436, 
            2569, 
            2598, 
            2600, 
            2456, 
            2624, 
            2485, 
            2454
        ], 
        "id": 1049
    }, 
    {
        "username": "effervescentecho", 
        "user_firstname": "", 
        "user_lastname": "", 
        "created_at": "2023-05-30T18:40:05.829106+02:00", 
        "telephone": "+43650430192", 
        "id": 1050, 
        "active": true, 
        "banana_points": 0, 
        "profile_img": "/images/blankuser/profile_image.png", 
        "liked_posts": [
            2427, 
            2611, 
            2531, 
            2472
        ], 
        "email": "effervescentecho@foo.com"
    }, 
    {
        "username": "enigmaticmuse", 
        "user_firstname": "", 
        "user_lastname": "", 
        "created_at": "2023-05-30T18:40:05.872164+02:00", 
        "telephone": "+43650073032", 
        "email": "enigmaticmuse@foo.com", 
        "active": true, 
        "banana_points": 0, 
        "profile_img": "/images/blankuser/profile_image.png", 
        "liked_posts": [
            2593, 
            2598, 
            2560, 
            2477
        ], 
        "id": 1051
    }, 
    {
        "username": "mesmerizingmystery", 
        "user_firstname": "", 
        "user_lastname": "", 
        "created_at": "2023-05-30T18:40:05.942030+02:00", 
        "telephone": "+43650536202", 
        "id": 1052, 
        "liked_posts": [
            2655, 
            2547, 
            2520
        ], 
        "banana_points": 0, 
        "profile_img": "/images/blankuser/profile_image.png", 
        "active": true, 
        "email": "mesmerizingmystery@example.com"
    }, 
    {
        "username": "imaginativeitinerant", 
        "user_firstname": "", 
        "user_lastname": "", 
        "created_at": "2023-05-30T18:40:05.985093+02:00", 
        "telephone": "+43650554186", 
        "email": "imaginativeitinerant@test.com", 
        "active": true, 
        "banana_points": 0, 
        "profile_img": "/images/blankuser/profile_image.png", 
        "liked_posts": [
            2675, 
            2572, 
            2550, 
            2630, 
            2495, 
            2632, 
            2624, 
            2654
        ], 
        "id": 1053
    }, 
    {
        "username": "mythicalnomad", 
        "user_firstname": "", 
        "user_lastname": "", 
        "created_at": "2023-05-30T18:40:06.027248+02:00", 
        "telephone": "+43650054317", 
        "id": 1054, 
        "liked_posts": [
            2418, 
            2448, 
            2477, 
            2482
        ], 
        "banana_points": 0, 
        "profile_img": "/images/blankuser/profile_image.png", 
        "active": true, 
        "email": "mythicalnomad@foo.com"
    }, 
    {
        "username": "playfulpilgrim", 
        "user_firstname": "", 
        "user_lastname": "", 
        "created_at": "2023-05-30T18:40:06.073159+02:00", 
        "telephone": "+43650285323", 
        "email": "playfulpilgrim@example.com", 
        "liked_posts": [
            2571, 
            2564, 
            2463, 
            2622, 
            2491, 
            2666
        ], 
        "banana_points": 0, 
        "profile_img": "/images/blankuser/profile_image.png", 
        "active": true, 
        "id": 1055
    }, 
    {
        "username": "magicalmuse", 
        "user_firstname": "", 
        "user_lastname": "", 
        "created_at": "2023-05-30T18:40:06.114832+02:00", 
        "telephone": "+43650778396", 
        "id": 1056, 
        "active": true, 
        "banana_points": 0, 
        "profile_img": "/images/blankuser/profile_image.png", 
        "liked_posts": [
            2550, 
            2514, 
            2526
        ], 
        "email": "magicalmuse@foo.com"
    }, 
    {
        "username": "bewitchingnomad", 
        "user_firstname": "", 
        "user_lastname": "", 
        "created_at": "2023-05-30T18:40:06.167245+02:00", 
        "telephone": "+43650429943", 
        "email": "bewitchingnomad@example.com", 
        "liked_posts": [
            2661, 
            2682, 
            2448, 
            2521
        ], 
        "banana_points": 0, 
        "profile_img": "/images/blankuser/profile_image.png", 
        "active": true, 
        "id": 1057
    }, 
    {
        "username": "bewitchingnomad", 
        "user_firstname": "", 
        "user_lastname": "", 
        "created_at": "2023-05-30T18:40:06.211471+02:00", 
        "telephone": "+43650984074", 
        "id": 1058, 
        "active": true, 
        "banana_points": 0, 
        "profile_img": "/images/blankuser/profile_image.png", 
        "liked_posts": [
            2516, 
            2474
        ], 
        "email": "bewitchingnomad@test.com"
    }, 
    {
        "username": "midnightmarauder", 
        "user_firstname": "", 
        "user_lastname": "", 
        "created_at": "2023-05-30T18:40:06.285046+02:00", 
        "telephone": "+43650905266", 
        "email": "midnightmarauder@foo.com", 
        "liked_posts": [
            2645, 
            2464, 
            2482, 
            2437
        ], 
        "banana_points": 0, 
        "profile_img": "/images/blankuser/profile_image.png", 
        "active": true, 
        "id": 1059
    }, 
    {
        "username": "harmonicnomad", 
        "user_firstname": "", 
        "user_lastname": "", 
        "created_at": "2023-05-30T18:40:06.345547+02:00", 
        "telephone": "+43650041091", 
        "id": 1060, 
        "active": true, 
        "banana_points": 0, 
        "profile_img": "/images/blankuser/profile_image.png", 
        "liked_posts": [
            2551, 
            2505
        ], 
        "email": "harmonicnomad@foo.com"
    }, 
    {
        "username": "captivatingwanderer", 
        "user_firstname": "", 
        "user_lastname": "", 
        "created_at": "2023-05-30T18:40:06.389236+02:00", 
        "telephone": "+43650142635", 
        "email": "captivatingwanderer@test.com", 
        "active": true, 
        "banana_points": 0, 
        "profile_img": "/images/blankuser/profile_image.png", 
        "liked_posts": [
            2600, 
            2501, 
            2550, 
            2576, 
            2467
        ], 
        "id": 1061
    }, 
    {
        "username": "magneticmystery", 
        "user_firstname": "", 
        "user_lastname": "", 
        "created_at": "2023-05-30T18:40:06.438920+02:00", 
        "telephone": "+43650262838", 
        "id": 1062, 
        "liked_posts": [
            2649, 
            2647
        ], 
        "banana_points": 0, 
        "profile_img": "/images/blankuser/profile_image.png", 
        "active": true, 
        "email": "magneticmystery@foo.com"
    }, 
    {
        "username": "techguru", 
        "user_firstname": "", 
        "user_lastname": "", 
        "created_at": "2023-05-30T18:40:06.502385+02:00", 
        "telephone": "+43650061963", 
        "email": "techguru@foo.com", 
        "active": true, 
        "banana_points": 0, 
        "profile_img": "/images/blankuser/profile_image.png", 
        "liked_posts": [
            2591, 
            2459, 
            2576
        ], 
        "id": 1063
    }, 
    {
        "username": "enigmaticentity", 
        "user_firstname": "", 
        "user_lastname": "", 
        "created_at": "2023-05-30T18:40:06.571589+02:00", 
        "telephone": "+43650731602", 
        "id": 1064, 
        "liked_posts": [
            2676, 
            2471, 
            2575, 
            2569, 
            2610, 
            2467
        ], 
        "banana_points": 0, 
        "profile_img": "/images/blankuser/profile_image.png", 
        "active": true, 
        "email": "enigmaticentity@example.com"
    }, 
    {
        "username": "etherealwisp", 
        "user_firstname": "", 
        "user_lastname": "", 
        "created_at": "2023-05-30T18:40:06.637644+02:00", 
        "telephone": "+43650426310", 
        "email": "etherealwisp@example.com", 
        "active": true, 
        "banana_points": 0, 
        "profile_img": "/images/blankuser/profile_image.png", 
        "liked_posts": [
            2438, 
            2427, 
            2465, 
            2712, 
            2463, 
            2640, 
            2636
        ], 
        "id": 1065
    }, 
    {
        "username": "wanderingwhimsy", 
        "user_firstname": "", 
        "user_lastname": "", 
        "created_at": "2023-05-30T18:40:06.703310+02:00", 
        "telephone": "+43650550057", 
        "id": 1066, 
        "liked_posts": [
            2681, 
            2688
        ], 
        "banana_points": 0, 
        "profile_img": "/images/blankuser/profile_image.png", 
        "active": true, 
        "email": "wanderingwhimsy@test.com"
    }, 
    {
        "username": "enchantingecho", 
        "user_firstname": "", 
        "user_lastname": "", 
        "created_at": "2023-05-30T18:40:06.753229+02:00", 
        "telephone": "+43650234749", 
        "email": "enchantingecho@foo.com", 
        "liked_posts": [
            2640, 
            2489, 
            2502, 
            2643, 
            2453, 
            2507, 
            2518, 
            2693
        ], 
        "banana_points": 0, 
        "profile_img": "/images/blankuser/profile_image.png", 
        "active": true, 
        "id": 1067
    }, 
    {
        "username": "wonderstruckwanderer", 
        "user_firstname": "", 
        "user_lastname": "", 
        "created_at": "2023-05-30T18:40:06.857617+02:00", 
        "telephone": "+43650327238", 
        "id": 1068, 
        "active": true, 
        "banana_points": 0, 
        "profile_img": "/images/blankuser/profile_image.png", 
        "liked_posts": [
            2551, 
            2475, 
            2654, 
            2625, 
            2648, 
            2543, 
            2665
        ], 
        "email": "wonderstruckwanderer@foo.com"
    }, 
    {
        "username": "adventureseeker", 
        "user_firstname": "", 
        "user_lastname": "", 
        "created_at": "2023-05-30T18:40:06.920044+02:00", 
        "telephone": "+43650982884", 
        "email": "adventureseeker@foo.com", 
        "active": true, 
        "banana_points": 0, 
        "profile_img": "/images/blankuser/profile_image.png", 
        "liked_posts": [
            2708, 
            2648, 
            2455, 
            2415, 
            2486, 
            2545
        ], 
        "id": 1069
    }, 
    {
        "username": "dreamyspirit", 
        "user_firstname": "", 
        "user_lastname": "", 
        "created_at": "2023-05-30T18:40:06.963489+02:00", 
        "telephone": "+43650786061", 
        "id": 1070, 
        "active": true, 
        "banana_points": 0, 
        "profile_img": "/images/blankuser/profile_image.png", 
        "liked_posts": [
            2504, 
            2575, 
            2530, 
            2549
        ], 
        "email": "dreamyspirit@foo.com"
    }, 
    {
        "username": "stellaradventurer", 
        "user_firstname": "", 
        "user_lastname": "", 
        "created_at": "2023-05-30T18:40:07.036092+02:00", 
        "telephone": "+43650262697", 
        "email": "stellaradventurer@test.com", 
        "active": true, 
        "banana_points": 0, 
        "profile_img": "/images/blankuser/profile_image.png", 
        "liked_posts": [
            2443, 
            2475, 
            2706, 
            2675, 
            2564, 
            2534, 
            2551, 
            2447
        ], 
        "id": 1071
    }, 
    {
        "username": "enrapturedroamer", 
        "user_firstname": "", 
        "user_lastname": "", 
        "created_at": "2023-05-30T18:40:07.145691+02:00", 
        "telephone": "+43650529655", 
        "id": 1072, 
        "active": true, 
        "banana_points": 0, 
        "profile_img": "/images/blankuser/profile_image.png", 
        "liked_posts": [
            2475, 
            2421, 
            2651, 
            2468
        ], 
        "email": "enrapturedroamer@test.com"
    }, 
    {
        "username": "fancifulroamer", 
        "user_firstname": "", 
        "user_lastname": "", 
        "created_at": "2023-05-30T18:40:07.200831+02:00", 
        "telephone": "+43650906370", 
        "email": "fancifulroamer@foo.com", 
        "liked_posts": [
            2578, 
            2528, 
            2575, 
            2514, 
            2649, 
            2650
        ], 
        "banana_points": 0, 
        "profile_img": "/images/blankuser/profile_image.png", 
        "active": true, 
        "id": 1073
    }, 
    {
        "username": "mysticmuse", 
        "user_firstname": "", 
        "user_lastname": "", 
        "created_at": "2023-05-30T18:40:07.266051+02:00", 
        "telephone": "+43650867879", 
        "id": 1074, 
        "liked_posts": [
            2476, 
            2422, 
            2680, 
            2429, 
            2468, 
            2599, 
            2498
        ], 
        "banana_points": 0, 
        "profile_img": "/images/blankuser/profile_image.png", 
        "active": true, 
        "email": "mysticmuse@example.com"
    }, 
    {
        "username": "curiousmind", 
        "user_firstname": "", 
        "user_lastname": "", 
        "created_at": "2023-05-30T18:40:07.370329+02:00", 
        "telephone": "+43650199919", 
        "email": "curiousmind@test.com", 
        "active": true, 
        "banana_points": 0, 
        "profile_img": "/images/blankuser/profile_image.png", 
        "liked_posts": [
            2451, 
            2597, 
            2567
        ], 
        "id": 1075
    }, 
    {
        "username": "curiousmind", 
        "user_firstname": "", 
        "user_lastname": "", 
        "created_at": "2023-05-30T18:40:07.445219+02:00", 
        "telephone": "+43650468430", 
        "id": 1076, 
        "active": true, 
        "banana_points": 0, 
        "profile_img": "/images/blankuser/profile_image.png", 
        "liked_posts": [
            2581, 
            2479, 
            2551
        ], 
        "email": "curiousmind@example.com"
    }, 
    {
        "username": "spellboundseeker", 
        "user_firstname": "", 
        "user_lastname": "", 
        "created_at": "2023-05-30T18:40:07.490509+02:00", 
        "telephone": "+43650244867", 
        "email": "spellboundseeker@test.com", 
        "active": true, 
        "banana_points": 0, 
        "profile_img": "/images/blankuser/profile_image.png", 
        "liked_posts": [
            2607, 
            2693, 
            2628
        ], 
        "id": 1077
    }, 
    {
        "username": "mirthfulmuse", 
        "user_firstname": "", 
        "user_lastname": "", 
        "created_at": "2023-05-30T18:40:07.537291+02:00", 
        "telephone": "+43650869800", 
        "id": 1078, 
        "liked_posts": [
            2514, 
            2598, 
            2672, 
            2679, 
            2484
        ], 
        "banana_points": 0, 
        "profile_img": "/images/blankuser/profile_image.png", 
        "active": true, 
        "email": "mirthfulmuse@test.com"
    }, 
    {
        "username": "playfulpixie", 
        "user_firstname": "", 
        "user_lastname": "", 
        "created_at": "2023-05-30T18:40:07.581250+02:00", 
        "telephone": "+43650262430", 
        "email": "playfulpixie@example.com", 
        "active": true, 
        "banana_points": 0, 
        "profile_img": "/images/blankuser/profile_image.png", 
        "liked_posts": [
            2431
        ], 
        "id": 1079
    }, 
    {
        "username": "radiantwanderer", 
        "user_firstname": "", 
        "user_lastname": "", 
        "created_at": "2023-05-30T18:40:07.628594+02:00", 
        "telephone": "+43650065040", 
        "id": 1080, 
        "liked_posts": [
            2538, 
            2590, 
            2593, 
            2559, 
            2703, 
            2448, 
            2660
        ], 
        "banana_points": 0, 
        "profile_img": "/images/blankuser/profile_image.png", 
        "active": true, 
        "email": "radiantwanderer@test.com"
    }, 
    {
        "username": "quirkyunicorn", 
        "user_firstname": "", 
        "user_lastname": "", 
        "created_at": "2023-05-30T18:40:07.674006+02:00", 
        "telephone": "+43650951789", 
        "email": "quirkyunicorn@test.com", 
        "active": true, 
        "banana_points": 0, 
        "profile_img": "/images/blankuser/profile_image.png", 
        "liked_posts": [
            2494, 
            2595, 
            2415
        ], 
        "id": 1081
    }, 
    {
        "username": "luminousdreamer", 
        "user_firstname": "", 
        "user_lastname": "", 
        "created_at": "2023-05-30T18:40:07.721416+02:00", 
        "telephone": "+43650442617", 
        "id": 1082, 
        "liked_posts": [
            2701, 
            2489, 
            2560, 
            2622, 
            2502
        ], 
        "banana_points": 0, 
        "profile_img": "/images/blankuser/profile_image.png", 
        "active": true, 
        "email": "luminousdreamer@test.com"
    }, 
    {
        "username": "magneticmystery", 
        "user_firstname": "", 
        "user_lastname": "", 
        "created_at": "2023-05-30T18:40:07.766119+02:00", 
        "telephone": "+43650655491", 
        "email": "magneticmystery@example.com", 
        "liked_posts": [
            2597, 
            2506, 
            2480
        ], 
        "banana_points": 0, 
        "profile_img": "/images/blankuser/profile_image.png", 
        "active": true, 
        "id": 1083
    }, 
    {
        "username": "livelyspirit", 
        "user_firstname": "", 
        "user_lastname": "", 
        "created_at": "2023-05-30T18:40:07.809181+02:00", 
        "telephone": "+43650435513", 
        "id": 1084, 
        "active": true, 
        "banana_points": 0, 
        "profile_img": "/images/blankuser/profile_image.png", 
        "liked_posts": [
            2564, 
            2697, 
            2664, 
            2689, 
            2539, 
            2492
        ], 
        "email": "livelyspirit@example.com"
    }, 
    {
        "username": "whisperedwanderer", 
        "user_firstname": "", 
        "user_lastname": "", 
        "created_at": "2023-05-30T18:40:07.863785+02:00", 
        "telephone": "+43650457340", 
        "email": "whisperedwanderer@test.com", 
        "liked_posts": [
            2462, 
            2700
        ], 
        "banana_points": 0, 
        "profile_img": "/images/blankuser/profile_image.png", 
        "active": true, 
        "id": 1085
    }, 
    {
        "username": "mesmerizingmystery", 
        "user_firstname": "", 
        "user_lastname": "", 
        "created_at": "2023-05-30T18:40:07.946408+02:00", 
        "telephone": "+43650222594", 
        "id": 1086, 
        "liked_posts": [
            2456, 
            2572, 
            2486, 
            2561
        ], 
        "banana_points": 0, 
        "profile_img": "/images/blankuser/profile_image.png", 
        "active": true, 
        "email": "mesmerizingmystery@test.com"
    }, 
    {
        "username": "rhapsodicwanderer", 
        "user_firstname": "", 
        "user_lastname": "", 
        "created_at": "2023-05-30T18:40:08.033253+02:00", 
        "telephone": "+43650328910", 
        "email": "rhapsodicwanderer@test.com", 
        "liked_posts": [
            2599, 
            2497, 
            2468
        ], 
        "banana_points": 0, 
        "profile_img": "/images/blankuser/profile_image.png", 
        "active": true, 
        "id": 1087
    }, 
    {
        "username": "etherealwisp", 
        "user_firstname": "", 
        "user_lastname": "", 
        "created_at": "2023-05-30T18:40:08.079534+02:00", 
        "telephone": "+43650442898", 
        "id": 1088, 
        "liked_posts": [
            2600, 
            2415, 
            2628
        ], 
        "banana_points": 0, 
        "profile_img": "/images/blankuser/profile_image.png", 
        "active": true, 
        "email": "etherealwisp@foo.com"
    }, 
    {
        "username": "cosmicdreamer", 
        "user_firstname": "", 
        "user_lastname": "", 
        "created_at": "2023-05-30T18:40:08.134299+02:00", 
        "telephone": "+43650895903", 
        "email": "cosmicdreamer@example.com", 
        "liked_posts": [
            2645, 
            2669
        ], 
        "banana_points": 0, 
        "profile_img": "/images/blankuser/profile_image.png", 
        "active": true, 
        "id": 1089
    }, 
    {
        "username": "tricklingwisp", 
        "user_firstname": "", 
        "user_lastname": "", 
        "created_at": "2023-05-30T18:40:08.207665+02:00", 
        "telephone": "+43650671731", 
        "id": 1090, 
        "liked_posts": [
            2709, 
            2581, 
            2712, 
            2648, 
            2521, 
            2541, 
            2569
        ], 
        "banana_points": 0, 
        "profile_img": "/images/blankuser/profile_image.png", 
        "active": true, 
        "email": "tricklingwisp@test.com"
    }, 
    {
        "username": "bewitchedexplorer", 
        "user_firstname": "", 
        "user_lastname": "", 
        "created_at": "2023-05-30T18:40:08.274920+02:00", 
        "telephone": "+43650657422", 
        "email": "bewitchedexplorer@test.com", 
        "liked_posts": [
            2631, 
            2681, 
            2544, 
            2533, 
            2562, 
            2448
        ], 
        "banana_points": 0, 
        "profile_img": "/images/blankuser/profile_image.png", 
        "active": true, 
        "id": 1091
    }, 
    {
        "username": "stellaradventurer", 
        "user_firstname": "", 
        "user_lastname": "", 
        "created_at": "2023-05-30T18:40:08.331608+02:00", 
        "telephone": "+43650886121", 
        "id": 1092, 
        "active": true, 
        "banana_points": 0, 
        "profile_img": "/images/blankuser/profile_image.png", 
        "liked_posts": [
            2631, 
            2599, 
            2617, 
            2712
        ], 
        "email": "stellaradventurer@foo.com"
    }, 
    {
        "username": "fantasyquest", 
        "user_firstname": "", 
        "user_lastname": "", 
        "created_at": "2023-05-30T18:40:08.406926+02:00", 
        "telephone": "+43650613354", 
        "email": "fantasyquest@foo.com", 
        "active": true, 
        "banana_points": 0, 
        "profile_img": "/images/blankuser/profile_image.png", 
        "liked_posts": [
            2454, 
            2671
        ], 
        "id": 1093
    }, 
    {
        "username": "silkysmooth", 
        "user_firstname": "", 
        "user_lastname": "", 
        "created_at": "2023-05-30T18:40:08.475897+02:00", 
        "telephone": "+43650484585", 
        "id": 1094, 
        "active": true, 
        "banana_points": 0, 
        "profile_img": "/images/blankuser/profile_image.png", 
        "liked_posts": [
            2464, 
            2589, 
            2623
        ], 
        "email": "silkysmooth@example.com"
    }, 
    {
        "username": "luminousdreamer", 
        "user_firstname": "", 
        "user_lastname": "", 
        "created_at": "2023-05-30T18:40:08.542559+02:00", 
        "telephone": "+43650777654", 
        "email": "luminousdreamer@example.com", 
        "liked_posts": [
            2496, 
            2471
        ], 
        "banana_points": 0, 
        "profile_img": "/images/blankuser/profile_image.png", 
        "active": true, 
        "id": 1095
    }, 
    {
        "username": "fantasylover", 
        "user_firstname": "", 
        "user_lastname": "", 
        "created_at": "2023-05-30T18:40:08.687442+02:00", 
        "telephone": "+43650496020", 
        "id": 1096, 
        "active": true, 
        "banana_points": 0, 
        "profile_img": "/images/blankuser/profile_image.png", 
        "liked_posts": [
            2471, 
            2439, 
            2588, 
            2687, 
            2569, 
            2665, 
            2651, 
            2702, 
            2619, 
            2414, 
            2676, 
            2678, 
            2528
        ], 
        "email": "fantasylover@example.com"
    }, 
    {
        "username": "bewitchingnomad", 
        "user_firstname": "", 
        "user_lastname": "", 
        "created_at": "2023-05-30T18:40:08.744908+02:00", 
        "telephone": "+43650155863", 
        "email": "bewitchingnomad@foo.com", 
        "active": true, 
        "banana_points": 0, 
        "profile_img": "/images/blankuser/profile_image.png", 
        "liked_posts": [
            2629
        ], 
        "id": 1097
    }, 
    {
        "username": "inspiringwanderer", 
        "user_firstname": "", 
        "user_lastname": "", 
        "created_at": "2023-05-30T18:40:08.813163+02:00", 
        "telephone": "+43650503123", 
        "id": 1098, 
        "active": true, 
        "banana_points": 0, 
        "profile_img": "/images/blankuser/profile_image.png", 
        "liked_posts": [
            2658, 
            2694
        ], 
        "email": "inspiringwanderer@foo.com"
    }, 
    {
        "username": "mythicalnomad", 
        "user_firstname": "", 
        "user_lastname": "", 
        "created_at": "2023-05-30T18:40:08.871857+02:00", 
        "telephone": "+43650238451", 
        "email": "mythicalnomad@test.com", 
        "active": true, 
        "banana_points": 0, 
        "profile_img": "/images/blankuser/profile_image.png", 
        "liked_posts": [
            2506, 
            2587, 
            2590, 
            2605, 
            2577, 
            2458, 
            2621
        ], 
        "id": 1099
    }, 
    {
        "username": "mysteriousroamer", 
        "user_firstname": "", 
        "user_lastname": "", 
        "created_at": "2023-05-30T18:40:08.929734+02:00", 
        "telephone": "+43650493405", 
        "id": 1100, 
        "liked_posts": [
            2656, 
            2587, 
            2546, 
            2599
        ], 
        "banana_points": 0, 
        "profile_img": "/images/blankuser/profile_image.png", 
        "active": true, 
        "email": "mysteriousroamer@foo.com"
    }, 
    {
        "username": "fantasylover", 
        "user_firstname": "", 
        "user_lastname": "", 
        "created_at": "2023-05-30T18:40:09.039959+02:00", 
        "telephone": "+43650915504", 
        "email": "fantasylover@foo.com", 
        "liked_posts": [
            2584, 
            2560, 
            2537, 
            2667, 
            2668, 
            2516, 
            2593, 
            2599, 
            2512, 
            2637
        ], 
        "banana_points": 0, 
        "profile_img": "/images/blankuser/profile_image.png", 
        "active": true, 
        "id": 1101
    }, 
    {
        "username": "wistfulwonder", 
        "user_firstname": "", 
        "user_lastname": "", 
        "created_at": "2023-05-30T18:40:09.092463+02:00", 
        "telephone": "+43650468134", 
        "id": 1102, 
        "liked_posts": [
            2631, 
            2551, 
            2423, 
            2548, 
            2501, 
            2537, 
            2493
        ], 
        "banana_points": 0, 
        "profile_img": "/images/blankuser/profile_image.png", 
        "active": true, 
        "email": "wistfulwonder@foo.com"
    }, 
    {
        "username": "illuminatedmuse", 
        "user_firstname": "", 
        "user_lastname": "", 
        "created_at": "2023-05-30T18:40:09.185206+02:00", 
        "telephone": "+43650404497", 
        "email": "illuminatedmuse@example.com", 
        "liked_posts": [
            2518, 
            2647, 
            2598, 
            2652
        ], 
        "banana_points": 0, 
        "profile_img": "/images/blankuser/profile_image.png", 
        "active": true, 
        "id": 1103
    }, 
    {
        "username": "bewitchingwanderlust", 
        "user_firstname": "", 
        "user_lastname": "", 
        "created_at": "2023-05-30T18:40:09.236733+02:00", 
        "telephone": "+43650532426", 
        "id": 1104, 
        "active": true, 
        "banana_points": 0, 
        "profile_img": "/images/blankuser/profile_image.png", 
        "liked_posts": [
            2495
        ], 
        "email": "bewitchingwanderlust@example.com"
    }, 
    {
        "username": "radiantwanderer", 
        "user_firstname": "", 
        "user_lastname": "", 
        "created_at": "2023-05-30T18:40:09.284588+02:00", 
        "telephone": "+43650256897", 
        "email": "radiantwanderer@foo.com", 
        "liked_posts": [
            2705, 
            2535, 
            2588
        ], 
        "banana_points": 0, 
        "profile_img": "/images/blankuser/profile_image.png", 
        "active": true, 
        "id": 1105
    }, 
    {
        "username": "whisperingwanderer", 
        "user_firstname": "", 
        "user_lastname": "", 
        "created_at": "2023-05-30T18:40:09.418695+02:00", 
        "telephone": "+43650390971", 
        "id": 1106, 
        "liked_posts": [
            2551, 
            2565, 
            2451, 
            2686, 
            2455, 
            2685
        ], 
        "banana_points": 0, 
        "profile_img": "/images/blankuser/profile_image.png", 
        "active": true, 
        "email": "whisperingwanderer@example.com"
    }, 
    {
        "username": "illuminatedmuse", 
        "user_firstname": "", 
        "user_lastname": "", 
        "created_at": "2023-05-30T18:40:09.466886+02:00", 
        "telephone": "+43650216110", 
        "email": "illuminatedmuse@test.com", 
        "liked_posts": [
            2521, 
            2488, 
            2589
        ], 
        "banana_points": 0, 
        "profile_img": "/images/blankuser/profile_image.png", 
        "active": true, 
        "id": 1107
    }, 
    {
        "username": "wistfulwonder", 
        "user_firstname": "", 
        "user_lastname": "", 
        "created_at": "2023-05-30T18:40:09.549476+02:00", 
        "telephone": "+43650143513", 
        "id": 1108, 
        "active": true, 
        "banana_points": 0, 
        "profile_img": "/images/blankuser/profile_image.png", 
        "liked_posts": [
            2634, 
            2462, 
            2465
        ], 
        "email": "wistfulwonder@test.com"
    }, 
    {
        "username": "etherealwanderlust", 
        "user_firstname": "", 
        "user_lastname": "", 
        "created_at": "2023-05-30T18:40:09.616031+02:00", 
        "telephone": "+43650038233", 
        "email": "etherealwanderlust@example.com", 
        "liked_posts": [
            2614
        ], 
        "banana_points": 0, 
        "profile_img": "/images/blankuser/profile_image.png", 
        "active": true, 
        "id": 1109
    }, 
    {
        "username": "blissfulitinerant", 
        "user_firstname": "", 
        "user_lastname": "", 
        "created_at": "2023-05-30T18:40:09.685862+02:00", 
        "telephone": "+43650621189", 
        "id": 1110, 
        "active": true, 
        "banana_points": 0, 
        "profile_img": "/images/blankuser/profile_image.png", 
        "liked_posts": [
            2445, 
            2542, 
            2700
        ], 
        "email": "blissfulitinerant@example.com"
    }, 
    {
        "username": "creativechameleon", 
        "user_firstname": "", 
        "user_lastname": "", 
        "created_at": "2023-05-30T18:40:09.912961+02:00", 
        "telephone": "+43650560151", 
        "email": "creativechameleon@foo.com", 
        "liked_posts": [
            2680, 
            2685, 
            2486, 
            2697
        ], 
        "banana_points": 0, 
        "profile_img": "/images/blankuser/profile_image.png", 
        "active": true, 
        "id": 1111
    }, 
    {
        "username": "effervescentecho", 
        "user_firstname": "", 
        "user_lastname": "", 
        "created_at": "2023-05-30T18:40:09.998743+02:00", 
        "telephone": "+43650036343", 
        "id": 1112, 
        "active": true, 
        "banana_points": 0, 
        "profile_img": "/images/blankuser/profile_image.png", 
        "liked_posts": [
            2596, 
            2515, 
            2469, 
            2682, 
            2434
        ], 
        "email": "effervescentecho@example.com"
    }, 
    {
        "username": "captivatingwanderer", 
        "user_firstname": "", 
        "user_lastname": "", 
        "created_at": "2023-05-30T18:40:10.065938+02:00", 
        "telephone": "+43650800998", 
        "email": "captivatingwanderer@example.com", 
        "active": true, 
        "banana_points": 0, 
        "profile_img": "/images/blankuser/profile_image.png", 
        "liked_posts": [
            2666, 
            2504, 
            2627
        ], 
        "id": 1113
    }, 
    {
        "username": "inspiringwanderer", 
        "user_firstname": "", 
        "user_lastname": "", 
        "created_at": "2023-05-30T18:40:10.133133+02:00", 
        "telephone": "+43650331134", 
        "id": 1114, 
        "liked_posts": [
            2449, 
            2545, 
            2575, 
            2594, 
            2501, 
            2439, 
            2618
        ], 
        "banana_points": 0, 
        "profile_img": "/images/blankuser/profile_image.png", 
        "active": true, 
        "email": "inspiringwanderer@example.com"
    }, 
    {
        "username": "whisperingwisp", 
        "user_firstname": "", 
        "user_lastname": "", 
        "created_at": "2023-05-30T18:40:10.207750+02:00", 
        "telephone": "+43650424478", 
        "email": "whisperingwisp@foo.com", 
        "liked_posts": [
            2437, 
            2636, 
            2647, 
            2501, 
            2599
        ], 
        "banana_points": 0, 
        "profile_img": "/images/blankuser/profile_image.png", 
        "active": true, 
        "id": 1115
    }, 
    {
        "username": "wanderingwhimsy", 
        "user_firstname": "", 
        "user_lastname": "", 
        "created_at": "2023-05-30T18:40:10.253875+02:00", 
        "telephone": "+43650251841", 
        "id": 1116, 
        "active": true, 
        "banana_points": 0, 
        "profile_img": "/images/blankuser/profile_image.png", 
        "liked_posts": [
            2550, 
            2537, 
            2501, 
            2570, 
            2578
        ], 
        "email": "wanderingwhimsy@foo.com"
    }, 
    {
        "username": "fancifulroamer", 
        "user_firstname": "", 
        "user_lastname": "", 
        "created_at": "2023-05-30T18:40:10.320993+02:00", 
        "telephone": "+43650864088", 
        "email": "fancifulroamer@example.com", 
        "liked_posts": [
            2701, 
            2500, 
            2608, 
            2562, 
            2444
        ], 
        "banana_points": 0, 
        "profile_img": "/images/blankuser/profile_image.png", 
        "active": true, 
        "id": 1117
    }, 
    {
        "username": "serendipitousmuse", 
        "user_firstname": "", 
        "user_lastname": "", 
        "created_at": "2023-05-30T18:40:10.392008+02:00", 
        "telephone": "+43650497684", 
        "id": 1118, 
        "liked_posts": [
            2459, 
            2434, 
            2479
        ], 
        "banana_points": 0, 
        "profile_img": "/images/blankuser/profile_image.png", 
        "active": true, 
        "email": "serendipitousmuse@test.com"
    }, 
    {
        "username": "livelyspirit", 
        "user_firstname": "", 
        "user_lastname": "", 
        "created_at": "2023-05-30T18:40:10.482115+02:00", 
        "telephone": "+43650858116", 
        "email": "livelyspirit@foo.com", 
        "banana_points": 0, 
        "profile_img": "/images/blankuser/profile_image.png", 
        "active": true, 
        "id": 1119
    }, 
    {
        "username": "mysterymaven", 
        "user_firstname": "", 
        "user_lastname": "", 
        "created_at": "2023-05-30T18:40:10.569812+02:00", 
        "telephone": "+43650880956", 
        "id": 1120, 
        "liked_posts": [
            2596, 
            2499, 
            2467, 
            2428, 
            2494, 
            2489
        ], 
        "banana_points": 0, 
        "profile_img": "/images/blankuser/profile_image.png", 
        "active": true, 
        "email": "mysterymaven@foo.com"
    }, 
    {
        "username": "blissfulitinerant", 
        "user_firstname": "", 
        "user_lastname": "", 
        "created_at": "2023-05-30T18:40:10.716492+02:00", 
        "telephone": "+43650486514", 
        "email": "blissfulitinerant@test.com", 
        "active": true, 
        "banana_points": 0, 
        "profile_img": "/images/blankuser/profile_image.png", 
        "liked_posts": [
            2536, 
            2617, 
            2508
        ], 
        "id": 1121
    }, 
    {
        "username": "serendipitysearcher", 
        "user_firstname": "", 
        "user_lastname": "", 
        "created_at": "2023-05-30T18:40:10.780367+02:00", 
        "telephone": "+43650174106", 
        "id": 1122, 
        "liked_posts": [
            2696, 
            2668, 
            2523
        ], 
        "banana_points": 0, 
        "profile_img": "/images/blankuser/profile_image.png", 
        "active": true, 
        "email": "serendipitysearcher@test.com"
    }
]